drf_payments/__init__.py
drf_payments/authorizenet/__init__.py
drf_payments/braintree/__init__.py
drf_payments/constants.py
drf_payments/core.py
drf_payments/mixins.py
drf_payments/models.py
drf_payments/paypal/__init__.py
drf_payments/stripe/__init__.py
drf_payments/urls.py
drf_payments-0.0.2.dist-info/LICENSE
drf_payments-0.0.2.dist-info/METADATA
drf_payments-0.0.2.dist-info/WHEEL
drf_payments-0.0.2.dist-info/RECORD
