Metadata-Version: 2.1
Name: drf-payments
Version: 0.0.2
Summary: Package to handle various payments provider inside your drf project
License: MIT
Author: Oleksandr Korol
Author-email: oleksandr.korol@coaxsoft.com
Requires-Python: >=3.8
Classifier: Framework :: Django
Classifier: Framework :: Django :: 3.2
Classifier: Framework :: Django :: 4.0
Classifier: Framework :: Django :: 4.1
Classifier: Framework :: Django :: 4.2
Classifier: Intended Audience :: Developers
Classifier: License :: OSI Approved :: BSD License
Classifier: License :: OSI Approved :: MIT License
Classifier: Operating System :: OS Independent
Classifier: Programming Language :: Python
Classifier: Programming Language :: Python :: 3
Classifier: Programming Language :: Python :: 3.8
Classifier: Programming Language :: Python :: 3.9
Classifier: Programming Language :: Python :: 3.10
Classifier: Programming Language :: Python :: 3.11
Requires-Dist: Django (>3.2.0)
Requires-Dist: braintree (>=4.20.0,<5.0.0)
Requires-Dist: django-phonenumber-field[phonenumberslite] (>=7.1.0,<8.0.0)
Requires-Dist: djangorestframework (>=3.14.0,<4.0.0)
Requires-Dist: drf-yasg (>=1.21.5,<2.0.0)
Requires-Dist: stripe (>=5.4,<6.0)
